<?xml version="1.0" encoding="ISO-8859-1"?>
<!DOCTYPE sect1 PUBLIC "-//OASIS//DTD DocBook XML V4.5//EN"
   "http://www.oasis-open.org/docbook/xml/4.5/docbookx.dtd" [
  <!ENTITY changelogs  "http://www.linuxfromscratch.org/blfs">
  <!ENTITY % general-entities SYSTEM "../../general.ent">
  %general-entities;
]>

<!-- vim: set expandtab: -->

<sect1 id="changelog" xreflabel="Change Log">
  <?dbhtml filename="changelog.html"?>

  <sect1info>
    <othername>$LastChangedBy$</othername>
    <date>$Date$</date>
  </sect1info>

  <title>Change Log</title>

  <!-- <para>Please note that the Change Log only lists which editor was
  responsible for putting the changes into SVN; please read the
  <xref linkend="credits"/> page in Chapter 1 for details on
  who wrote what.</para> -->

  <para>Current release: &version; &ndash; &releasedate;</para>

  <itemizedlist>
    <title>Changelog Entries:</title>

<!-- Changelog template
    <listitem>
      <para>MMMM DD{nd,st,th}, YYYY</para>
      <itemizedlist>
        <listitem>
          <para>[name] - Changelog entry.</para>
        </listitem>
        <listitem>
          <para>[name] - Another changelog entry.</para>
        </listitem>
      </itemizedlist>
    </listitem>
    -->
   <listitem>
     <para>March 3rd, 2021</para>
     <itemizedlist>
       <listitem>
         <para>[bdubbs] - Update to nano-5.6.1. Fixes
         <ulink url="&blfs-ticket-root;14727">#14727</ulink>.</para>
       </listitem>
       <listitem>
         <para>[bdubbs] - Update to mousepad-0.5.3. Fixes
         <ulink url="&blfs-ticket-root;14718">#14718</ulink>.</para>
       </listitem>
       <listitem>
         <para>[bdubbs] - Update to liblinear-243. Fixes
         <ulink url="&blfs-ticket-root;14709">#14709</ulink>.</para>
       </listitem>
       <listitem>
         <para>[bdubbs] - Update to libwacom-1.9. Fixes
         <ulink url="&blfs-ticket-root;14703">#14703</ulink>.</para>
       </listitem>
       <listitem>
         <para>[bdubbs] - Update to libiodbc-3.52.14. Fixes
         <ulink url="&blfs-ticket-root;14702">#14702</ulink>.</para>
       </listitem>
       <listitem>
         <para>[bdubbs] - Update to gtkmm3-3.24.4. Fixes
         <ulink url="&blfs-ticket-root;14701">#14701</ulink>.</para>
       </listitem>
       <listitem>
         <para>[bdubbs] - Update to gtk+3 3.24.26. Fixes
         <ulink url="&blfs-ticket-root;14700">#14700</ulink>.</para>
       </listitem>
       <listitem>
         <para>[renodr] - Update to vala-0.50.4. Fixes
         <ulink url="&blfs-ticket-root;14719">#14719</ulink>.</para>
       </listitem>
       <listitem>
         <para>[renodr] - Update to cbindgen-0.18.0. Fixes
         <ulink url="&blfs-ticket-root;14717">#14717</ulink>.</para>
       </listitem>
       <listitem>
         <para>[renodr] - Update to mariadb-10.5.9. Fixes
         <ulink url="&blfs-ticket-root;14699">#14699</ulink>.</para>
       </listitem>
       <listitem>
         <para>[renodr] - Update to cmake-3.19.6. Fixes
         <ulink url="&blfs-ticket-root;14710">#14710</ulink>.</para>
       </listitem>
     </itemizedlist>
   </listitem>

   <listitem>
      <para>March 2nd, 2021</para>
      <itemizedlist>
        <listitem>
          <para>[pierre] - Force usage of python3 for cracklib bindings.</para>
        </listitem>
        <listitem>
          <para>[pierre] - Fix a header file in python, so that
          <command>#include &lt;python&python3-majorver;/Python.h&gt;</command>
          works.</para>
        </listitem>
        <listitem>
          <para>[thomas] - Fix a seccomp issue in OpenSSH on non-x86_64 platforms.</para>
        </listitem>
        <listitem>
          <para>[ken] - Update to nss-3.62. Fixes
          <ulink url="&blfs-ticket-root;14684">#14684</ulink>.</para>
        </listitem>
        <listitem>
          <para>[bdubbs] - Update to xorgproto-2021.3. Fixes
          <ulink url="&blfs-ticket-root;14711">#14711</ulink>.</para>
        </listitem>
        <listitem>
          <para>[bdubbs] - Update to libinput-1.17.0 (Xorg Driver). Fixes
          <ulink url="&blfs-ticket-root;14706">#14706</ulink>.</para>
        </listitem>
        <listitem>
          <para>[bdubbs] - Update to IO-Socket-SSL-2.070 (Perl module). Fixes
          <ulink url="&blfs-ticket-root;14716">#14716</ulink>.</para>
        </listitem>
        <listitem>
          <para>[bdubbs] - Update to libqmi-1.28.0. Fixes
          <ulink url="&blfs-ticket-root;14697">#14697</ulink>.</para>
        </listitem>
        <listitem>
          <para>[bdubbs] - Update to ibus-1.5.24. Fixes
          <ulink url="&blfs-ticket-root;14693">#14693</ulink>.</para>
        </listitem>
      </itemizedlist>
    </listitem>

   <listitem>
      <para>March 1st, 2021</para>
      <itemizedlist>
        <listitem>
          <para>[timtas] - Update to icewm-2.2.0. Fixes
          <ulink url="&blfs-ticket-root;14720">#14720</ulink>.</para>
        </listitem>
        <listitem>
          <para>[bdubbs] - Release of BLFS-10.1.</para>
        </listitem>
      </itemizedlist>
    </listitem>

  </itemizedlist>
</sect1>
