<?xml version="1.0" encoding="ISO-8859-1"?>
<!DOCTYPE sect1 PUBLIC "-//OASIS//DTD DocBook XML V4.5//EN"
   "http://www.oasis-open.org/docbook/xml/4.5/docbookx.dtd" [
  <!ENTITY changelogs  "http://www.linuxfromscratch.org/blfs">
  <!ENTITY % general-entities SYSTEM "../../general.ent">
  %general-entities;
]>

<!-- vim: set expandtab: -->

<sect1 id="changelog" xreflabel="Change Log">
  <?dbhtml filename="changelog.html"?>

  <sect1info>
    <othername>$LastChangedBy$</othername>
    <date>$Date$</date>
  </sect1info>

  <title>Change Log</title>

  <!-- <para>Please note that the Change Log only lists which editor was
  responsible for putting the changes into SVN; please read the
  <xref linkend="credits"/> page in Chapter 1 for details on
  who wrote what.</para> -->

  <para>Current release: &version; &ndash; &releasedate;</para>

  <itemizedlist>
    <title>Changelog Entries:</title>

<!-- Changelog template
    <listitem>
      <para>MMMM DD{nd,st,th}, YYYY</para>
      <itemizedlist>
        <listitem>
          <para>[name] - Changelog entry.</para>
        </listitem>
        <listitem>
          <para>[name] - Another changelog entry.</para>
        </listitem>
      </itemizedlist>
    </listitem>
    -->
    <listitem>
      <para>March 17th, 2021</para>
      <itemizedlist>
        <listitem>
          <para>[renodr] - Update to goffice-0.10.49. Fixes
          <ulink url="&blfs-ticket-root;14772">#14772</ulink>.</para>
        </listitem>
        <listitem>
          <para>[renodr] - Update to pyatspi-2.38.1. Fixes
          <ulink url="&blfs-ticket-root;14769">#14769</ulink>.</para>
        </listitem>
        <listitem>
          <para>[renodr] - Update the gstreamer stack to gst*-1.18.4. Includes
          updates for five security vulnerabilities. Fixes
          <ulink url="&blfs-ticket-root;14776">#14776</ulink>.</para>
        </listitem>
      </itemizedlist>
    </listitem>

    <listitem>
      <para>March 16th, 2021</para>
      <itemizedlist>
        <listitem>
          <para>[renodr] - Update to exo-4.16.1. Fixes
          <ulink url="&blfs-ticket-root;14759">#14759</ulink>.</para>
        </listitem>
        <listitem>
          <para>[renodr] - Update to libhandy-1.2.0. Fixes
          <ulink url="&blfs-ticket-root;14760">#14760</ulink>.</para>
        </listitem>
        <listitem>
          <para>[renodr] - Update to NetworkManager-1.30.2. Fixes
          <ulink url="&blfs-ticket-root;14761">#14761</ulink>.</para>
        </listitem>
        <listitem>
          <para>[renodr] - Update to gtk+-3.24.27. Fixes
          <ulink url="&blfs-ticket-root;14762">#14762</ulink>.</para>
        </listitem>
        <listitem>
          <para>[renodr] - Update to epiphany-3.38.3. Fixes
          <ulink url="&blfs-ticket-root;14763">#14763</ulink>.</para>
        </listitem>
        <listitem>
          <para>[renodr] - Update to dconf-0.40.0. Fixes
          <ulink url="&blfs-ticket-root;14764">#14764</ulink>.</para>
        </listitem>
        <listitem>
          <para>[renodr] - Update to xfsprogs-5.11.0. Fixes
          <ulink url="&blfs-ticket-root;14765">#14765</ulink>.</para>
        </listitem>
        <listitem>
          <para>[renodr] - Update to libgusb-0.3.6. Fixes
          <ulink url="&blfs-ticket-root;14766">#14766</ulink>.</para>
        </listitem>
        <listitem>
          <para>[renodr] - Update to sqlite-3.35.1. Fixes
          <ulink url="&blfs-ticket-root;14767">#14767</ulink>.</para>
        </listitem>
        <listitem>
          <para>[renodr] - Update to wireshark-3.4.4 (Security Update). Fixes
          <ulink url="&blfs-ticket-root;14751">#14751</ulink>.</para>
        </listitem>
        <listitem>
          <para>[renodr] - Update to pango-1.48.3. Fixes
          <ulink url="&blfs-ticket-root;14753">#14753</ulink>.</para>
        </listitem>
        <listitem>
          <para>[renodr] - Update to cryptsetup-2.3.5. Fixes
          <ulink url="&blfs-ticket-root;14754">#14754</ulink>.</para>
        </listitem>
        <listitem>
          <para>[renodr] - Update to gptfdisk-1.0.7. Fixes
          <ulink url="&blfs-ticket-root;14755">#14755</ulink>.</para>
        </listitem>
        <listitem>
          <para>[renodr] - Update to libxkbcommon-1.1.0. Fixes
          <ulink url="&blfs-ticket-root;14756">#14756</ulink>.</para>
        </listitem>
        <listitem>
          <para>[renodr] - Update to qpdf-10.3.1. Fixes
          <ulink url="&blfs-ticket-root;14757">#14757</ulink>.</para>
        </listitem>
      </itemizedlist>
    </listitem>

    <listitem>
      <para>March 15th, 2021</para>
      <itemizedlist>
        <listitem>
          <para>[ken] - Update to asymptote-2.70. Fixes
          <ulink url="&blfs-ticket-root;14774">#14774</ulink>.</para>
        </listitem>
        <listitem>
          <para>[timtas] - Update to sudo-1.9.6. Fixes
          <ulink url="&blfs-ticket-root;14771">#14771</ulink>.</para>
        </listitem>
      </itemizedlist>
    </listitem>

    <listitem>
      <para>March 14th, 2021</para>
      <itemizedlist>
        <listitem>
          <para>[ken] - Update to mutt-2.0.6. Fixes
          <ulink url="&blfs-ticket-root;14742">#14742</ulink>.</para>
        </listitem>
        <listitem>
          <para>[xry111] - Update to gnome-autoar-0.3.1.
          Fixes <ulink url="&blfs-ticket-root;14768">#14768</ulink>.</para>
        </listitem>
        <listitem>
          <para>[renodr] - Update to iso-codes-4.6.0. Fixes
          <ulink url="&blfs-ticket-root;14744">#14744</ulink>.</para>
        </listitem>
        <listitem>
          <para>[renodr] - Update to Thunderbird-78.8.1. Fixes
          <ulink url="&blfs-ticket-root;14745">#14745</ulink>.</para>
        </listitem>
        <listitem>
          <para>[renodr] - Update to git-2.30.2. Fixes
          <ulink url="&blfs-ticket-root;14746">#14746</ulink>.</para>
        </listitem>
        <listitem>
          <para>[renodr] - Update to mercurial-5.7.1. Fixes
          <ulink url="&blfs-ticket-root;14747">#14747</ulink>.</para>
        </listitem>
        <listitem>
          <para>[renodr] - Update to samba-4.14.0. Fixes
          <ulink url="&blfs-ticket-root;14748">#14748</ulink>.</para>
        </listitem>
      </itemizedlist>
    </listitem>

    <listitem>
      <para>March 12th, 2021</para>
      <itemizedlist>
        <listitem>
          <para>[renodr] - Update to libreoffice-7.1.1.2. Fixes
          <ulink url="&blfs-ticket-root;14734">#14734</ulink>.</para>
        </listitem>
        <listitem>
          <para>[timtas] - Update to Thunar-4.16.5. Fixes
          <ulink url="&blfs-ticket-root;14752">#14752</ulink>.</para>
        </listitem>
        <listitem>
          <para>[xry111] - Update to GnuTLS-3.7.1 (with security fixes).
          Fixes <ulink url="&blfs-ticket-root;14750">#14750</ulink>.</para>
        </listitem>
      </itemizedlist>
    </listitem>

    <listitem>
      <para>March 11th, 2021</para>
      <itemizedlist>
        <listitem revision="systemd">
          <para>[renodr] - Make sure that the instructions for creating a
          symlink for /usr/lib/systemd in $KF5_PREFIX are still run when
          reinitializing /opt/kf5.</para>
        </listitem>
        <listitem>
          <para>[renodr] - Update to php-8.0.3. Fixes
          <ulink url="&blfs-ticket-root;14732">#14732</ulink>.</para>
        </listitem>
        <listitem>
          <para>[renodr] - Update to libgdata-0.18.1. Fixes
          <ulink url="&blfs-ticket-root;14736">#14736</ulink>.</para>
        </listitem>
        <listitem>
          <para>[renodr] - Update to HTML-Parser-3.76. Fixes
          <ulink url="&blfs-ticket-root;14731">#14731</ulink>.</para>
        </listitem>
        <listitem>
          <para>[ken] - Prevent a (mostly harmless) segfault when a urxvt
          term (from rxvt-unicode) shuts down.</para>
        </listitem>
      </itemizedlist>
    </listitem>

    <listitem>
      <para>March 10th, 2021</para>
      <itemizedlist>
        <listitem>
          <para>[ken] - Add a patch to mupdf to fix a security issue. Fixes
          <ulink url="&blfs-ticket-root;14749">#14749</ulink>.</para>
        </listitem>
        <listitem>
          <para>[ken] - Add a caution about unpatched security vulnerabilities
          in QtWebEngine and Falkon. Addresses
          <ulink url="&blfs-ticket-root;14729">#14729</ulink>.</para>
        </listitem>
      </itemizedlist>
    </listitem>

    <listitem>
      <para>March 8th, 2021</para>
      <itemizedlist>
        <listitem>
          <para>[timtas] - Update to fetchmail-6.4.17. Fixes
          <ulink url="&blfs-ticket-root;14743">#14743</ulink>.</para>
        </listitem>
      </itemizedlist>
    </listitem>

    <listitem>
      <para>March 7th, 2021</para>
      <itemizedlist>
        <listitem>
          <para>[pierre] - Update to unrar-6.0.4. Fixes
          <ulink url="&blfs-ticket-root;14740">#14740</ulink>.</para>
        </listitem>
        <listitem>
          <para>[pierre] - Update to qpdf-10.3.0. Fixes
          <ulink url="&blfs-ticket-root;14739">#14739</ulink>.</para>
        </listitem>
        <listitem>
          <para>[pierre] - Update to jasper-2.0.26. Fixes
          <ulink url="&blfs-ticket-root;14738">#14738</ulink>.</para>
        </listitem>
        <listitem>
          <para>[pierre] - Update to btrfs-progs-5.11. Fixes
          <ulink url="&blfs-ticket-root;14737">#14737</ulink>.</para>
        </listitem>
      </itemizedlist>
    </listitem>

    <listitem revision="sysv">
      <para>March 6th, 2021</para>
      <itemizedlist>
        <listitem>
          <para>[pierre] - Update to elogind-246.10. Fixes
          <ulink url="&blfs-ticket-root;14726">#14726</ulink>.</para>
        </listitem>
      </itemizedlist>
    </listitem>

    <listitem>
      <para>March 5th, 2021</para>
      <itemizedlist>
        <listitem>
          <para>[timtas] - Update to dovecot-2.3.14. Fixes
          <ulink url="&blfs-ticket-root;14733">#14733</ulink>.</para>
        </listitem>
      </itemizedlist>
    </listitem>

    <listitem revision="systemd">
      <para>March 4th, 2021</para>
      <itemizedlist>
        <listitem>
          <para>[renodr] - Update the systemd patch to allow systemd-rfkill
          to still function properly once LFS gets updated to Linux-5.11.</para>
        </listitem>
      </itemizedlist>
    </listitem>

    <listitem>
      <para>March 3rd, 2021</para>
      <itemizedlist>
        <listitem>
          <para>[renodr] - Update to URI-5.09 (Perl Module). Fixes
          <ulink url="&blfs-ticket-root;14723">#14723</ulink>.</para>
        </listitem>
        <listitem>
          <para>[renodr] - Update to OpenSSH-8.5p1 (and ssh-askpass-8.5p1).
          Includes a security fix for ssh-agent. Fixes
          <ulink url="&blfs-ticket-root;14725">#14725</ulink>.</para>
        </listitem>
        <listitem>
          <para>[renodr] - Update to gtksourceview-4.8.1. Includes a patch to
          prevent a race condition on some systems. Fixes
          <ulink url="&blfs-ticket-root;14724">#14724</ulink>.</para>
        </listitem>
        <listitem>
          <para>[renodr] - Update to poppler-21.03.0. Fixes
          <ulink url="&blfs-ticket-root;14722">#14722</ulink>.</para>
        </listitem>
        <listitem>
          <para>[renodr] - Update to babl-0.1.86. Fixes
          <ulink url="&blfs-ticket-root;14715">#14715</ulink>.</para>
        </listitem>
        <listitem>
          <para>[renodr] - Update to libgxps-0.3.2. Fixes
          <ulink url="&blfs-ticket-root;14714">#14714</ulink>.</para>
        </listitem>
        <listitem>
          <para>[renodr] - Update to qpdf-10.2.0. Fixes
          <ulink url="&blfs-ticket-root;14707">#14707</ulink>.</para>
        </listitem>
        <listitem>
          <para>[renodr] - Update to libqmi-1.28.2. Fixes
          <ulink url="&blfs-ticket-root;14721">#14721</ulink>.</para>
        </listitem>
        <listitem>
          <para>[renodr] - Update to ModemManager-1.16.2. Fixes
          <ulink url="&blfs-ticket-root;14705">#14705</ulink>.</para>
        </listitem>
        <listitem>
          <para>[bdubbs] - Update to bluez-5.56. Fixes
          <ulink url="&blfs-ticket-root;14698">#14698</ulink>.</para>
        </listitem>
        <listitem>
          <para>[bdubbs] - Update to nano-5.6.1. Fixes
          <ulink url="&blfs-ticket-root;14727">#14727</ulink>.</para>
        </listitem>
        <listitem>
          <para>[bdubbs] - Update to mousepad-0.5.3. Fixes
          <ulink url="&blfs-ticket-root;14718">#14718</ulink>.</para>
        </listitem>
        <listitem>
          <para>[bdubbs] - Update to liblinear-243. Fixes
          <ulink url="&blfs-ticket-root;14709">#14709</ulink>.</para>
        </listitem>
        <listitem>
          <para>[bdubbs] - Update to libwacom-1.9. Fixes
          <ulink url="&blfs-ticket-root;14703">#14703</ulink>.</para>
        </listitem>
        <listitem>
          <para>[bdubbs] - Update to libiodbc-3.52.14. Fixes
          <ulink url="&blfs-ticket-root;14702">#14702</ulink>.</para>
        </listitem>
        <listitem>
          <para>[bdubbs] - Update to gtkmm3-3.24.4. Fixes
          <ulink url="&blfs-ticket-root;14701">#14701</ulink>.</para>
        </listitem>
        <listitem>
          <para>[bdubbs] - Update to gtk+3 3.24.26. Fixes
          <ulink url="&blfs-ticket-root;14700">#14700</ulink>.</para>
        </listitem>
        <listitem>
          <para>[renodr] - Update to vala-0.50.4. Fixes
          <ulink url="&blfs-ticket-root;14719">#14719</ulink>.</para>
        </listitem>
        <listitem>
          <para>[renodr] - Update to cbindgen-0.18.0. Fixes
          <ulink url="&blfs-ticket-root;14717">#14717</ulink>.</para>
        </listitem>
        <listitem>
          <para>[renodr] - Update to mariadb-10.5.9. Fixes
          <ulink url="&blfs-ticket-root;14699">#14699</ulink>.</para>
        </listitem>
        <listitem>
          <para>[renodr] - Update to cmake-3.19.6. Fixes
          <ulink url="&blfs-ticket-root;14710">#14710</ulink>.</para>
        </listitem>
      </itemizedlist>
    </listitem>

    <listitem>
      <para>March 2nd, 2021</para>
      <itemizedlist>
        <listitem>
          <para>[pierre] - Force usage of python3 for cracklib bindings.</para>
        </listitem>
        <listitem>
          <para>[pierre] - Fix a header file in python, so that
          <command>#include &lt;python&python3-majorver;/Python.h&gt;</command>
          works.</para>
        </listitem>
        <listitem>
          <para>[thomas] - Fix a seccomp issue in OpenSSH on non-x86_64
          platforms.</para>
        </listitem>
        <listitem>
          <para>[ken] - Update to nss-3.62. Fixes
          <ulink url="&blfs-ticket-root;14684">#14684</ulink>.</para>
        </listitem>
        <listitem>
          <para>[bdubbs] - Update to xorgproto-2021.3. Fixes
          <ulink url="&blfs-ticket-root;14711">#14711</ulink>.</para>
        </listitem>
        <listitem>
          <para>[bdubbs] - Update to libinput-1.17.0 (Xorg Driver). Fixes
          <ulink url="&blfs-ticket-root;14706">#14706</ulink>.</para>
        </listitem>
        <listitem>
          <para>[bdubbs] - Update to IO-Socket-SSL-2.070 (Perl module). Fixes
          <ulink url="&blfs-ticket-root;14716">#14716</ulink>.</para>
        </listitem>
        <listitem>
          <para>[bdubbs] - Update to libqmi-1.28.0. Fixes
          <ulink url="&blfs-ticket-root;14697">#14697</ulink>.</para>
        </listitem>
        <listitem>
          <para>[bdubbs] - Update to ibus-1.5.24. Fixes
          <ulink url="&blfs-ticket-root;14693">#14693</ulink>.</para>
        </listitem>
      </itemizedlist>
    </listitem>

    <listitem>
      <para>March 1st, 2021</para>
      <itemizedlist>
        <listitem>
          <para>[timtas] - Update to icewm-2.2.0. Fixes
          <ulink url="&blfs-ticket-root;14720">#14720</ulink>.</para>
        </listitem>
        <listitem>
          <para>[bdubbs] - Release of BLFS-10.1.</para>
        </listitem>
      </itemizedlist>
    </listitem>

  </itemizedlist>
</sect1>
