<?xml version="1.0" encoding="ISO-8859-1"?>
<!DOCTYPE note PUBLIC "-//OASIS//DTD DocBook XML V4.5//EN"
  "http://www.oasis-open.org/docbook/xml/4.5/docbookx.dtd">
<!-- Automatically generated by kernel-config.py
     DO NOT EDIT! -->
<screen>[*] N<emphasis role='blue'>e</emphasis>tworking support ---&gt;                                                [NET]
  N<emphasis role='blue'>e</emphasis>tworking options ---&gt;
    [*] N<emphasis role='blue'>e</emphasis>twork packet filtering framework (Netfilter) ---&gt;          [NETFILTER]
      [*] <emphasis role='blue'>A</emphasis>dvanced netfilter configuration                  [NETFILTER_ADVANCED]
      <emphasis role='blue'>C</emphasis>ore Netfilter Configuration ---&gt;
        &lt;*/M&gt; N<emphasis role='blue'>e</emphasis>tfilter connection tracking support               [NF_CONNTRACK]
        &lt;*/M&gt; N<emphasis role='blue'>e</emphasis>tfilter Xtables support (required for ip_tables)
                                                        ...  [NETFILTER_XTABLES]
        &lt;*/M&gt;   <emphasis role='blue'>L</emphasis>OG target support                     [NETFILTER_XT_TARGET_LOG]
      <emphasis role='blue'>I</emphasis>P: Netfilter Configuration ---&gt;
        &lt;*/M&gt; <emphasis role='blue'>I</emphasis>P tables support (required for filtering/masq/NAT)
                                                           ...  [IP_NF_IPTABLES]</screen>
